Metadata-Version: 2.1
Name: dragonfly2
Version: 0.35.0
Summary: Speech recognition extension library
Home-page: https://github.com/dictation-toolbox/dragonfly
Author: Christo Butcher
Author-email: dist.dragonfly@twizzy.biz
Maintainer: Dane Finlay
Maintainer-email: Danesprite@posteo.net
License: LICENSE.txt
Platform: UNKNOWN
Classifier: Development Status :: 4 - Beta
Classifier: Environment :: Win32 (MS Windows)
Classifier: Environment :: X11 Applications
Classifier: Environment :: MacOS X
Classifier: License :: OSI Approved :: GNU Library or Lesser General Public License (LGPL)
Classifier: Intended Audience :: Developers
Classifier: Operating System :: Microsoft :: Windows
Classifier: Operating System :: POSIX
Classifier: Operating System :: MacOS
Classifier: Programming Language :: Python :: 2.7
Classifier: Programming Language :: Python :: 3.4
Classifier: Programming Language :: Python :: 3.5
Classifier: Programming Language :: Python :: 3.6
Classifier: Programming Language :: Python :: 3.7
Classifier: Programming Language :: Python :: Implementation :: CPython
Classifier: Topic :: Multimedia :: Sound/Audio :: Speech
Classifier: Topic :: Software Development :: Libraries :: Python Modules
License-File: LICENSE.txt
License-File: AUTHORS.txt
Requires-Dist: setuptools (>=40.0.0)
Requires-Dist: packaging (>=19.0)
Requires-Dist: six
Requires-Dist: pyperclip (>=1.7.0)
Requires-Dist: regex
Requires-Dist: decorator
Requires-Dist: lark-parser (==0.8.*)
Requires-Dist: json-rpc
Requires-Dist: Werkzeug
Requires-Dist: requests
Requires-Dist: pynput (>=1.4.2) ; platform_system == "Darwin"
Requires-Dist: pyobjc (>=5.2) ; platform_system == "Darwin"
Requires-Dist: py-applescript (==1.0.0) ; platform_system == "Darwin"
Requires-Dist: psutil (>=5.5.1) ; platform_system == "Linux"
Requires-Dist: comtypes ; platform_system == "Windows"
Requires-Dist: pywin32 ; platform_system == "Windows"
Requires-Dist: enum34 ; python_version < "3.4"
Provides-Extra: kaldi
Requires-Dist: kaldi-active-grammar (~=3.1.0) ; extra == 'kaldi'
Requires-Dist: sounddevice (==0.3.*) ; extra == 'kaldi'
Requires-Dist: webrtcvad-wheels (==2.0.*) ; extra == 'kaldi'
Provides-Extra: sphinx
Requires-Dist: sphinxwrapper (>=1.2.0) ; extra == 'sphinx'
Requires-Dist: pyjsgf (>=1.7.0) ; extra == 'sphinx'
Requires-Dist: pyaudio ; extra == 'sphinx'
